{
  "gitSyncId": "673eb342e443011fab9eaa76_55df5416-8fec-462c-9342-3f4904050666",
  "id": "AgencyPage_getsub",
  "pluginId": "restapi-plugin",
  "pluginType": "API",
  "unpublishedAction": {
    "actionConfiguration": {
      "autoGeneratedHeaders": [],
      "body": "",
      "bodyFormData": [],
      "encodeParamsToggle": true,
      "formData": {
        "apiContentType": "none"
      },
      "headers": [],
      "httpMethod": "GET",
      "httpVersion": "HTTP11",
      "paginationType": "NONE",
      "path": "api/sub/subscribe/",
      "pluginSpecifiedTemplates": [
        {
          "value": true
        }
      ],
      "queryParameters": [],
      "timeoutInMillisecond": 10000
    },
    "confirmBeforeExecute": false,
    "datasource": {
      "id": "APInoAuthorization",
      "isAutoGenerated": false,
      "name": "APInoAuthorization",
      "pluginId": "restapi-plugin"
    },
    "dynamicBindingPathList": [],
    "executeOnLoad": true,
    "name": "getsub",
    "pageId": "AgencyPage",
    "userSetOnLoad": false
  }
}